inka/__init__.py
inka/__main__.py
inka/cli.py
inka/exceptions.py
inka/helpers.py
inka/mistune_plugins/__init__.py
inka/mistune_plugins/mathjax.py
inka/models/__init__.py
inka/models/anki_api.py
inka/models/anki_media.py
inka/models/config.py
inka/models/converter.py
inka/models/hasher.py
inka/models/highlighter.py
inka/models/img_handler.py
inka/models/parser.py
inka/models/writer.py
inka/models/notes/__init__.py
inka/models/notes/basic_note.py
inka/models/notes/cloze_note.py
inka/models/notes/note.py
inka-2.2.3.dist-info/LICENSE
inka-2.2.3.dist-info/METADATA
inka-2.2.3.dist-info/WHEEL
inka-2.2.3.dist-info/entry_points.txt
inka-2.2.3.dist-info/top_level.txt
inka-2.2.3.dist-info/RECORD
