Metadata-Version: 2.1
Name: inka
Version: 2.2.3
Summary: Command-line tool for adding flashcards from Markdown files to Anki
Home-page: https://github.com/keiqu/inka
Author: Kirill Salnikov
Author-email: salnikov.k54@gmail.com
License: GPLv3
Keywords: anki,markdown,spaced-repetition
Classifier: Development Status :: 5 - Production/Stable
Classifier: Operating System :: OS Independent
Classifier: Intended Audience :: Education
Classifier: Topic :: Education :: Computer Aided Instruction (CAI)
Classifier: Topic :: Text Processing :: Markup :: Markdown
Classifier: License :: OSI Approved :: GNU General Public License v3 (GPLv3)
Classifier: Programming Language :: Python :: 3
Classifier: Programming Language :: Python :: 3.10
Classifier: Programming Language :: Python :: 3.11
Classifier: Programming Language :: Python :: 3 :: Only
Requires-Python: >=3.10
License-File: LICENSE
Requires-Dist: mistune (==2.0.5)
Requires-Dist: requests (==2.28.2)
Requires-Dist: click (==8.1.3)
Requires-Dist: rich (==13.3.3)
Requires-Dist: PyQt6 (~=6.5)
Requires-Dist: PyQt6-WebEngine (~=6.5)
Requires-Dist: aqt (>=2.1.61)
